pyrsqrd/__init__.py
pyrsqrd-0.0.0.dist-info/METADATA
pyrsqrd-0.0.0.dist-info/WHEEL
pyrsqrd-0.0.0.dist-info/top_level.txt
pyrsqrd-0.0.0.dist-info/RECORD
