Metadata-Version: 2.1
Name: pyrsqrd
Version: 0.0.0
Summary: Reactive structured queryable relational data
Author-email: Ben Howell <ben@psychstudio.com>
Classifier: Programming Language :: Python :: 3
Classifier: License :: OSI Approved :: MIT License
Classifier: Operating System :: OS Independent
Requires-Python: >=3.10
